unifiedbooster/__init__.py
unifiedbooster/gbdt.py
unifiedbooster/gbdt_classification.py
unifiedbooster/gbdt_regression.py
unifiedbooster/gpoptimization.py
unifiedbooster-0.4.2.dist-info/LICENSE
unifiedbooster-0.4.2.dist-info/METADATA
unifiedbooster-0.4.2.dist-info/WHEEL
unifiedbooster-0.4.2.dist-info/entry_points.txt
unifiedbooster-0.4.2.dist-info/top_level.txt
unifiedbooster-0.4.2.dist-info/RECORD
